MANIFEST.in
README.md
pyproject.toml
requirements.txt
requirements_test.txt
setup.py
mindsdb_native/__about__.py
mindsdb_native/__init__.py
mindsdb_native/scraps.py
mindsdb_native.egg-info/PKG-INFO
mindsdb_native.egg-info/SOURCES.txt
mindsdb_native.egg-info/dependency_links.txt
mindsdb_native.egg-info/requires.txt
mindsdb_native.egg-info/top_level.txt
mindsdb_native/config/__init__.py
mindsdb_native/config/helpers.py
mindsdb_native/external_libs/__init__.py
mindsdb_native/external_libs/stats.py
mindsdb_native/libs/__init__.py
mindsdb_native/libs/constants/__init__.py
mindsdb_native/libs/constants/mindsdb.py
mindsdb_native/libs/controllers/__init__.py
mindsdb_native/libs/controllers/functional.py
mindsdb_native/libs/controllers/predictor.py
mindsdb_native/libs/controllers/transaction.py
mindsdb_native/libs/data_types/__init__.py
mindsdb_native/libs/data_types/mindsdb_logger.py
mindsdb_native/libs/data_types/transaction_data.py
mindsdb_native/libs/data_types/transaction_output_data.py
mindsdb_native/libs/data_types/transaction_output_row.py
mindsdb_native/libs/helpers/__init__.py
mindsdb_native/libs/helpers/accuracy_stats.py
mindsdb_native/libs/helpers/confidence_helpers.py
mindsdb_native/libs/helpers/conformal_helpers.py
mindsdb_native/libs/helpers/date_helpers.py
mindsdb_native/libs/helpers/general_helpers.py
mindsdb_native/libs/helpers/json_helpers.py
mindsdb_native/libs/helpers/locking.py
mindsdb_native/libs/helpers/mp_helpers.py
mindsdb_native/libs/helpers/multi_data_source.py
mindsdb_native/libs/helpers/parser.py
mindsdb_native/libs/helpers/query_composer.py
mindsdb_native/libs/helpers/sqlite_helpers.py
mindsdb_native/libs/helpers/stats_helpers.py
mindsdb_native/libs/helpers/text_helpers.py
mindsdb_native/libs/helpers/train_helpers.py
mindsdb_native/libs/phases/__init__.py
mindsdb_native/libs/phases/base_module.py
mindsdb_native/libs/phases/data_analyzer/__init__.py
mindsdb_native/libs/phases/data_analyzer/data_analyzer.py
mindsdb_native/libs/phases/data_cleaner/__init__.py
mindsdb_native/libs/phases/data_cleaner/data_cleaner.py
mindsdb_native/libs/phases/data_extractor/__init__.py
mindsdb_native/libs/phases/data_extractor/data_extractor.py
