Metadata-Version: 2.1
Name: mindsdb-native
Version: 2.48.0
Summary: MindsDB's goal is to make it very simple for developers to use the power of artificial neural networks in their projects.
Home-page: https://github.com/mindsdb/mindsdb_native
Author: MindsDB Inc
Author-email: jorge@mindsdb.com
License: GPL-3.0
Download-URL: https://pypi.org/project/mindsdb
Platform: UNKNOWN
Classifier: Programming Language :: Python :: 3
Classifier: License :: OSI Approved :: MIT License
Classifier: Operating System :: OS Independent
Requires-Python: >=3.6
